gerador_endereco.py
gerador_endereco-1.0.15.dist-info/LICENSE
gerador_endereco-1.0.15.dist-info/METADATA
gerador_endereco-1.0.15.dist-info/WHEEL
gerador_endereco-1.0.15.dist-info/top_level.txt
gerador_endereco-1.0.15.dist-info/RECORD
