Metadata-Version: 2.1
Name: gerador-endereco
Version: 1.0.15
Summary: API para criação de endereços aleatórios em um município específico.
Home-page: https://github.com/open-dsa/gerador_endereco
Download-URL: https://github.com/open-dsa/gerador_endereco
Author: Michel Metran
Author-email: michelmetran@gmail.com
Maintainer: Michel Metran
Maintainer-email: michelmetran@gmail.com
License: MIT
Project-URL: Documentation, https://github.com/open-dsa/gerador_endereco#readme
Project-URL: Issue Tracker, https://github.com/open-dsa/gerador_endereco/issues
Project-URL: Source Code, https://github.com/open-dsa/gerador_endereco
Keywords: python,endereço aleatório,address
Platform: any
Classifier: Development Status :: 1 - Planning
Classifier: Intended Audience :: Developers
Classifier: License :: OSI Approved :: MIT License
Classifier: Natural Language :: Portuguese
Classifier: Natural Language :: Portuguese (Brazilian)
Classifier: Operating System :: OS Independent
Classifier: Programming Language :: Python
Classifier: Programming Language :: Python :: 3
Classifier: Programming Language :: Python :: 3 :: Only
Requires-Python: >=3.6
License-File: LICENSE
Requires-Dist: pycep-correios (>=5.0.0)
Requires-Dist: requests (>=2.10.0)
